windowlayout/__init__.py
windowlayout/__main__.py
windowlayout/switcher.py
windowlayout/window.py
windowlayout-0.0.1.dist-info/LICENSE
windowlayout-0.0.1.dist-info/METADATA
windowlayout-0.0.1.dist-info/WHEEL
windowlayout-0.0.1.dist-info/top_level.txt
windowlayout-0.0.1.dist-info/RECORD
