Metadata-Version: 2.1
Name: windowlayout
Version: 0.0.1
Summary: Manages a layout of windows
Home-page: https://github.com/mi25iw/windowlayout
Author: mi25iw
License: UNKNOWN
Project-URL: Bug Tracker, https://github.com/mi25iw/windowlayout/issues
Platform: UNKNOWN
Classifier: Programming Language :: Python :: 3
Classifier: License :: OSI Approved :: MIT License
Classifier: Operating System :: Microsoft :: Windows :: Windows 10
Requires-Python: >=3.6
License-File: LICENSE
Requires-Dist: pywin32
Requires-Dist: psutil
